pycodetags_issue_tracker/__about__.py
pycodetags_issue_tracker/__init__.py
pycodetags_issue_tracker/_tag_templates.txt.md
pycodetags_issue_tracker/cli.py
pycodetags_issue_tracker/converters.py
pycodetags_issue_tracker/main.py
pycodetags_issue_tracker/plugin_manager.py
pycodetags_issue_tracker/plugin_specs.py
pycodetags_issue_tracker/config/__init__.py
pycodetags_issue_tracker/config/issue_tracker_config.py
pycodetags_issue_tracker/schema/__init__.py
pycodetags_issue_tracker/schema/issue_tracker_aliases.py
pycodetags_issue_tracker/schema/issue_tracker_classes.py
pycodetags_issue_tracker/schema/issue_tracker_schema.py
pycodetags_issue_tracker/user_utils/__init__.py
pycodetags_issue_tracker/user_utils/user.py
pycodetags_issue_tracker/user_utils/users_from_authors.py
pycodetags_issue_tracker/views/__init__.py
pycodetags_issue_tracker/views/health_o_meter.py
pycodetags_issue_tracker/views/views.py
pycodetags_issue_tracker/views/views_templated.py
pycodetags_issue_tracker/views/templates/__init__.py
pycodetags_issue_tracker/views/templates/report.html.jinja2
pycodetags_issue_tracker-0.3.0.dist-info/METADATA
pycodetags_issue_tracker-0.3.0.dist-info/WHEEL
pycodetags_issue_tracker-0.3.0.dist-info/entry_points.txt
pycodetags_issue_tracker-0.3.0.dist-info/RECORD
