Metadata-Version: 2.4
Name: pycodetags-issue-tracker
Version: 0.3.0
Summary: Plugin for pycodetags to track issues, e.g. bugs, TODO, etc in your code
Author-email: Matthew Martin <matthewdeanmartin@gmail.com>
License-Expression: MIT
Keywords: FIXME,TODO,code-tag,code-tags,codetag,codetags,pep-350,pep350,pycodetags
Classifier: Development Status :: 4 - Beta
Classifier: Intended Audience :: Developers
Classifier: License :: OSI Approved :: MIT License
Classifier: Operating System :: OS Independent
Classifier: Programming Language :: Python
Classifier: Programming Language :: Python :: 3.7
Classifier: Programming Language :: Python :: 3.8
Classifier: Programming Language :: Python :: 3.9
Classifier: Programming Language :: Python :: 3.10
Classifier: Programming Language :: Python :: 3.11
Classifier: Programming Language :: Python :: 3.12
Classifier: Programming Language :: Python :: 3.13
Classifier: Programming Language :: Python :: 3.14
Requires-Python: >=3.7
Requires-Dist: importlib-resources; python_version < '3.9'
Requires-Dist: jinja2
Requires-Dist: pluggy
Requires-Dist: pycodetags>=0.6.0
Requires-Dist: toml; python_version < '3.11'
Requires-Dist: typing-extensions; python_version < '3.8'
